stum/cli.py
stum/contours.py
stum/east.py
stum/tesseract.py
stum/video_to_srt.py
stum-0.2.0.dist-info/METADATA
stum-0.2.0.dist-info/WHEEL
stum-0.2.0.dist-info/entry_points.txt
stum-0.2.0.dist-info/licenses/LICENSE
stum-0.2.0.dist-info/RECORD
