Metadata-Version: 2.4
Name: stum
Version: 0.2.0
Summary: Tool for detecting and extracting text from intertitles in Swedish newsreels.
Project-URL: Homepage, https://github.com/Modern36/stum
Project-URL: Bug Tracker, https://github.com/Modern36/stum/issues
Author-email: Mathias Johansson <MathiasJoha@gmail.com>
Maintainer-email: Mathias Johansson <MathiasJoha@gmail.com>
License: CC-BY-NC-4.0
License-File: LICENSE
Keywords: automatic speech recognition,intertitle,newsreels,speech-to-text,swedish,transcription
Classifier: Development Status :: 4 - Beta
Classifier: Framework :: Pytest
Classifier: Intended Audience :: Science/Research
Classifier: Operating System :: MacOS
Classifier: Operating System :: POSIX :: Linux
Classifier: Programming Language :: Python :: 3.10
Classifier: Programming Language :: Python :: 3.11
Classifier: Programming Language :: Python :: 3.12
Classifier: Programming Language :: Python :: 3.13
Classifier: Topic :: Multimedia :: Video
Classifier: Topic :: Scientific/Engineering :: Image Processing
Classifier: Topic :: Utilities
Requires-Python: >=3.10
Requires-Dist: jiwer>=3.1.0
Requires-Dist: opencv-contrib-python>=4.11.0.86
Requires-Dist: pytesseract>=0.3.13
Requires-Dist: python-ffmpeg>=2.0.12
Requires-Dist: tqdm>=4.67.1
Provides-Extra: dev
Requires-Dist: coverage-badge==1.1.2; extra == 'dev'
Requires-Dist: coverage==7.5.1; extra == 'dev'
Requires-Dist: pre-commit==4.1.0; extra == 'dev'
Requires-Dist: pytest-cov==5.0.0; extra == 'dev'
Requires-Dist: pytest-xdist==3.6.1; extra == 'dev'
Requires-Dist: pytest==8.2.0; extra == 'dev'
